nexusbridge/__init__.py
nexusbridge/base.py
nexusbridge/binance/authentication.py
nexusbridge/binance/base.py
nexusbridge/binance/cm/__init__.py
nexusbridge/binance/cm/account.py
nexusbridge/binance/cm/general.py
nexusbridge/binance/cm/market_data.py
nexusbridge/binance/cm/trade.py
nexusbridge/binance/cm/user_data_stream.py
nexusbridge/binance/cm/web_socket_stream.py
nexusbridge/binance/constants.py
nexusbridge/binance/error.py
nexusbridge/binance/margin/__init__.py
nexusbridge/binance/margin/account.py
nexusbridge/binance/margin/history.py
nexusbridge/binance/pm/__init__.py
nexusbridge/binance/pm/account.py
nexusbridge/binance/pm/common.py
nexusbridge/binance/pm/trade.py
nexusbridge/binance/spot/__init__.py
nexusbridge/binance/spot/account.py
nexusbridge/binance/spot/general.py
nexusbridge/binance/spot/market_data.py
nexusbridge/binance/spot/trading.py
nexusbridge/binance/spot/user_data_stream.py
nexusbridge/binance/spot/web_socket_stream.py
nexusbridge/binance/um/__init__.py
nexusbridge/binance/um/account.py
nexusbridge/binance/um/convert.py
nexusbridge/binance/um/general.py
nexusbridge/binance/um/market_data.py
nexusbridge/binance/um/trade.py
nexusbridge/binance/um/user_data_stream.py
nexusbridge/binance/um/web_socket_stream.py
nexusbridge/bybit/api/__init__.py
nexusbridge/bybit/api/account.py
nexusbridge/bybit/api/asset.py
nexusbridge/bybit/api/market.py
nexusbridge/bybit/api/position.py
nexusbridge/bybit/api/trade.py
nexusbridge/bybit/constants.py
nexusbridge/bybit/error.py
nexusbridge/bybit/restapi.py
nexusbridge/bybit/wsapi.py
nexusbridge/config.py
nexusbridge/jupiter/__init__.py
nexusbridge/jupiter/jupiter.py
nexusbridge/okx/api/__init__.py
nexusbridge/okx/api/algo_trading.py
nexusbridge/okx/api/copy_trading.py
nexusbridge/okx/api/financial_product.py
nexusbridge/okx/api/grid_trading.py
nexusbridge/okx/api/market_data.py
nexusbridge/okx/api/public_data.py
nexusbridge/okx/api/recurring_buy.py
nexusbridge/okx/api/signal_bot_trading.py
nexusbridge-0.1.2.dist-info/LICENSE
nexusbridge-0.1.2.dist-info/METADATA
nexusbridge-0.1.2.dist-info/WHEEL
nexusbridge-0.1.2.dist-info/RECORD
