Metadata-Version: 2.3
Name: nexusbridge
Version: 0.1.2
Summary: A unified trading interface for major cryptocurrency exchanges, supporting REST APIs and WebSocket connections for Binance, OKX, Bybit and more.
License: MIT
Author: River-Shi
Author-email: nachuan.shi.quant@gmail.com
Requires-Python: >=3.11,<4.0
Classifier: License :: OSI Approved :: MIT License
Classifier: Programming Language :: Python :: 3
Classifier: Programming Language :: Python :: 3.11
Classifier: Programming Language :: Python :: 3.12
Classifier: Programming Language :: Python :: 3.13
Requires-Dist: aiohttp (>=3.11.11,<4.0.0)
Requires-Dist: aiolimiter (>=1.2.1,<2.0.0)
Requires-Dist: anchorpy (>=0.21.0,<0.22.0)
Requires-Dist: asynciolimiter (>=1.1.1,<2.0.0)
Requires-Dist: certifi (>=2024.12.14,<2025.0.0)
Requires-Dist: dynaconf (>=3.2.6,<4.0.0)
Requires-Dist: httpx (>=0.28.1,<0.29.0)
Requires-Dist: loguru (>=0.7.3,<0.8.0)
Requires-Dist: orjson (>=3.10.12,<4.0.0)
Requires-Dist: pathlib (>=1.0.1,<2.0.0)
Requires-Dist: picows (>=1.7.2,<2.0.0)
Requires-Dist: pycryptodome (>=3.21.0,<4.0.0)
